.gitignore
COC.md
COMMIT_EMOJI_CHEATSHEET.md
LICENSE.txt
MANIFEST.in
README.md
environ.py.dist
manage.py
requirements.txt
run.sh
settings.py
setup.py
urls.py
djember_model/__init__.py
djember_model/base.py
djember_model/urls.py
djember_model/views.py
djember_model.egg-info/PKG-INFO
djember_model.egg-info/SOURCES.txt
djember_model.egg-info/dependency_links.txt
djember_model.egg-info/requires.txt
djember_model.egg-info/top_level.txt
djember_model/management/__init__.py
djember_model/management/commands/__init__.py
djember_model/management/commands/export_to_ember.py
djember_model/migrations/__init__.py
djember_model/templates/djember_model/.ember_model_base.js.swp
djember_model/templates/djember_model/dynamic_model.js
djember_model/templates/djember_model/ember_model.js
djember_model/templates/djember_model/ember_model_base.js
djember_model/templates/djember_model/ember_model_test.js
docs/mkdocs.yml
docs/docs/index.md
sample/__init__.py
sample/models.py
sample/serializers.py
sample/views.py
sample/wsgi.py
sample/migrations/0001_initial.py
sample/migrations/0002_auto_20160627_1002.py
sample/migrations/__init__.py